<?xml version="1.0" encoding="utf-8" ?>
  
<Defs>

<FacialAnimation.HeadTypeDef>
<defName>AstorielHeadNormal</defName>
<texPath>Things/Pawn/Astoriel/Heads_Blank/Normal</texPath>
<raceName>Alien_Astoriel</raceName>
<shader>Map/CutoutSkin</shader>
</FacialAnimation.HeadTypeDef>

<FacialAnimation.HeadTypeDef>
<defName>AstorielHeadPointy</defName>
<texPath>Things/Pawn/Astoriel/Heads_Blank/Pointy</texPath>
<raceName>Alien_Astoriel</raceName>
<gender>Female</gender>
<shader>Map/CutoutSkin</shader>
</FacialAnimation.HeadTypeDef>

<FacialAnimation.HeadTypeDef>
<defName>AstorielHeadSquare</defName>
<texPath>Things/Pawn/Astoriel/Heads_Blank/Square</texPath>
<raceName>Alien_Astoriel</raceName>
<gender>Male</gender>
<shader>Map/CutoutSkin</shader>
</FacialAnimation.HeadTypeDef>

</Defs>